__init__.py
db_connection.py
main.py
query_normalizer.py
server.py
sql_validator.py
ms_fabric_mcp-0.1.5.dist-info/licenses/LICENSE
ms_fabric_mcp-0.1.5.dist-info/METADATA
ms_fabric_mcp-0.1.5.dist-info/WHEEL
ms_fabric_mcp-0.1.5.dist-info/entry_points.txt
ms_fabric_mcp-0.1.5.dist-info/top_level.txt
ms_fabric_mcp-0.1.5.dist-info/RECORD
