Metadata-Version: 2.4
Name: ms-fabric-mcp
Version: 0.1.5
Summary: MCP server to run SQL queries and explore schemas in MS Fabric items
Project-URL: Repository, https://github.com/duggurd/ms_fabric_mcp
Project-URL: Documentation, https://github.com/duggurd/ms_fabric_mcp/blob/master/README.md
Keywords: microsoft,fabric,ms-fabric,mcp,llm,warehouse,lakehouse
Requires-Python: >=3.10
License-File: LICENSE
Requires-Dist: azure-identity>=1.23.0
Requires-Dist: fastmcp>=2.3.4
Requires-Dist: pyodbc>=5.2.0
Requires-Dist: sqlparse>=0.5.3
Dynamic: license-file
